COPYRIGHT
LICENSE
MANIFEST.in
README
README.rst
setup.py
asyncssh/__init__.py
asyncssh/asn1.py
asyncssh/auth.py
asyncssh/channel.py
asyncssh/cipher.py
asyncssh/compression.py
asyncssh/connection.py
asyncssh/constants.py
asyncssh/curve25519.py
asyncssh/dh.py
asyncssh/dsa.py
asyncssh/ec.py
asyncssh/forward.py
asyncssh/kex.py
asyncssh/listen.py
asyncssh/mac.py
asyncssh/misc.py
asyncssh/packet.py
asyncssh/pbe.py
asyncssh/public_key.py
asyncssh/rsa.py
asyncssh/saslprep.py
asyncssh/stream.py
asyncssh_unofficial.egg-info/PKG-INFO
asyncssh_unofficial.egg-info/SOURCES.txt
asyncssh_unofficial.egg-info/dependency_links.txt
asyncssh_unofficial.egg-info/requires.txt
asyncssh_unofficial.egg-info/top_level.txt
examples/check_exit_status.py
examples/direct_client.py
examples/direct_server.py
examples/listening_client.py
examples/local_forwarding_client.py
examples/local_forwarding_client2.py
examples/local_forwarding_server.py
examples/math_client.py
examples/math_server.py
examples/remote_forwarding_client.py
examples/remote_forwarding_client2.py
examples/remote_forwarding_server.py
examples/set_environment.py
examples/set_terminal.py
examples/show_environment.py
examples/show_terminal.py
examples/simple_client.py
examples/simple_keyed_server.py
examples/simple_server.py
examples/stderr_client.py
examples/stream_direct_client.py
examples/stream_direct_server.py
examples/stream_listening_client.py
examples/stream_math_client.py
examples/stream_math_server.py
tests/__init__.py
tests/test_keys.py